<tree name="test"><node var="Age"><edge num="2" var="45-64"><node var="Region"><edge num="2" var="Midwest"><node var="Bush Approval"><edge num="0" var="Approve"><decision choice="McCain" end="1" p="1" /></edge><edge num="1" var="Disapprove"><decision choice="Obama" end="0" p="1" /></edge></node></edge><edge num="0" var="Northeast"><decision choice="Obama" end="0" p="1" /></edge><edge num="1" var="South"><decision choice="Obama" end="0" p="1" /></edge><edge num="3" var="West"><node var="Bush Approval"><edge num="1" var="Disapprove"><decision choice="Obama" end="0" p="1" /></edge><edge num="0" var="Approve"><decision choice="McCain" end="1" p="1" /></edge></node></edge></node></edge><edge num="3" var="65+"><node var="Region"><edge num="0" var="Northeast"><node var="Bush Approval"><edge num="1" var="Disapprove"><decision choice="Obama" end="0" p="1" /></edge><edge num="0" var="Approve"><decision choice="McCain" end="1" p="1" /></edge></node></edge><edge num="2" var="Midwest"><decision choice="McCain" end="1" p="1" /></edge><edge num="1" var="South"><decision choice="Obama" end="0" p="1" /></edge></node></edge><edge num="1" var="30-44"><decision choice="Obama" end="0" p="1" /></edge><edge num="0" var="18-29"><decision choice="Obama" end="0" p="1" /></edge></node><node var="Age"><edge num="1" var="30-44"><decision choice="Obama" end="0" p="1" /></edge><edge num="0" var="18-29"><decision choice="Obama" end="0" p="1" /></edge><edge num="2" var="45-64"><node var="Region"><edge num="0" var="Northeast"><node var="Bush Approval"><edge num="1" var="Disapprove"><decision choice="Obama" end="0" p="1" /></edge><edge num="0" var="Approve"><decision choice="Obama" end="0" p="1" /></edge></node></edge><edge num="1" var="South"><node var="Bush Approval"><edge num="1" var="Disapprove"><decision choice="Obama" end="0" p="1" /></edge><edge num="0" var="Approve"><decision choice="Obama" end="0" p="1" /></edge></node></edge><edge num="2" var="Midwest"><node var="Bush Approval"><edge num="1" var="Disapprove"><decision choice="Obama" end="0" p="1" /></edge><edge num="0" var="Approve"><decision choice="Obama" end="0" p="1" /></edge></node></edge><edge num="3" var="West"><decision choice="Obama" end="0" p="1" /></edge></node></edge><edge num="3" var="65+"><node var="Region"><edge num="3" var="West"><decision choice="Obama" end="0" p="1" /></edge><edge num="1" var="South"><decision choice="McCain" end="1" p="1" /></edge><edge num="0" var="Northeast"><node var="Bush Approval"><edge num="1" var="Disapprove"><decision choice="Obama" end="0" p="1" /></edge><edge num="0" var="Approve"><decision choice="McCain" end="1" p="1" /></edge></node></edge><edge num="2" var="Midwest"><decision choice="Obama" end="0" p="1" /></edge></node></edge></node><node var="Age"><edge num="0" var="18-29"><decision choice="Obama" end="0" p="1" /></edge><edge num="2" var="45-64"><node var="Region"><edge num="0" var="Northeast"><decision choice="Obama" end="0" p="1" /></edge><edge num="1" var="South"><node var="Bush Approval"><edge num="1" var="Disapprove"><decision choice="Obama" end="0" p="1" /></edge><edge num="0" var="Approve"><decision choice="Obama" end="0" p="1" /></edge></node></edge><edge num="2" var="Midwest"><node var="Bush Approval"><edge num="1" var="Disapprove"><decision choice="Obama" end="0" p="1" /></edge><edge num="0" var="Approve"><decision choice="Obama" end="0" p="1" /></edge></node></edge><edge num="3" var="West"><decision choice="Obama" end="0" p="1" /></edge></node></edge><edge num="1" var="30-44"><decision choice="Obama" end="0" p="1" /></edge><edge num="3" var="65+"><node var="Region"><edge num="1" var="South"><node var="Bush Approval"><edge num="1" var="Disapprove"><decision choice="Obama" end="0" p="1" /></edge><edge num="0" var="Approve"><decision choice="McCain" end="1" p="1" /></edge></node></edge><edge num="3" var="West"><decision choice="McCain" end="1" p="1" /></edge><edge num="2" var="Midwest"><decision choice="Obama" end="0" p="1" /></edge><edge num="0" var="Northeast"><node var="Bush Approval"><edge num="1" var="Disapprove"><decision choice="McCain" end="1" p="1" /></edge><edge num="0" var="Approve"><decision choice="Obama" end="0" p="1" /></edge></node></edge></node></edge></node><node var="Age"><edge num="1" var="30-44"><decision choice="Obama" end="0" p="1" /></edge><edge num="2" var="45-64"><node var="Region"><edge num="1" var="South"><node var="Bush Approval"><edge num="1" var="Disapprove"><decision choice="Obama" end="0" p="1" /></edge><edge num="0" var="Approve"><decision choice="Obama" end="0" p="1" /></edge></node></edge><edge num="3" var="West"><decision choice="Obama" end="0" p="1" /></edge><edge num="0" var="Northeast"><node var="Bush Approval"><edge num="0" var="Approve"><decision choice="Obama" end="0" p="1" /></edge><edge num="1" var="Disapprove"><decision choice="Obama" end="0" p="1" /></edge></node></edge><edge num="2" var="Midwest"><decision choice="Obama" end="0" p="1" /></edge></node></edge><edge num="3" var="65+"><node var="Region"><edge num="1" var="South"><node var="Bush Approval"><edge num="0" var="Approve"><decision choice="Obama" end="0" p="1" /></edge><edge num="1" var="Disapprove"><decision choice="Obama" end="0" p="1" /></edge></node></edge><edge num="2" var="Midwest"><node var="Bush Approval"><edge num="1" var="Disapprove"><decision choice="McCain" end="1" p="1" /></edge><edge num="0" var="Approve"><decision choice="Obama" end="0" p="1" /></edge></node></edge><edge num="0" var="Northeast"><node var="Bush Approval"><edge num="1" var="Disapprove"><decision choice="Obama" end="0" p="1" /></edge><edge num="0" var="Approve"><decision choice="McCain" end="1" p="1" /></edge></node></edge><edge num="3" var="West"><decision choice="Obama" end="0" p="1" /></edge></node></edge><edge num="0" var="18-29"><decision choice="Obama" end="0" p="1" /></edge></node><node var="Age"><edge num="2" var="45-64"><node var="Region"><edge num="2" var="Midwest"><decision choice="Obama" end="0" p="1" /></edge><edge num="0" var="Northeast"><decision choice="Obama" end="0" p="1" /></edge><edge num="1" var="South"><node var="Bush Approval"><edge num="1" var="Disapprove"><decision choice="Obama" end="0" p="1" /></edge><edge num="0" var="Approve"><decision choice="Obama" end="0" p="1" /></edge></node></edge><edge num="3" var="West"><node var="Bush Approval"><edge num="0" var="Approve"><decision choice="Obama" end="0" p="1" /></edge><edge num="1" var="Disapprove"><decision choice="Obama" end="0" p="1" /></edge></node></edge></node></edge><edge num="0" var="18-29"><decision choice="Obama" end="0" p="1" /></edge><edge num="1" var="30-44"><decision choice="Obama" end="0" p="1" /></edge><edge num="3" var="65+"><node var="Region"><edge num="0" var="Northeast"><node var="Bush Approval"><edge num="0" var="Approve"><decision choice="McCain" end="1" p="1" /></edge><edge num="1" var="Disapprove"><decision choice="McCain" end="1" p="1" /></edge></node></edge><edge num="1" var="South"><node var="Bush Approval"><edge num="0" var="Approve"><decision choice="Obama" end="0" p="1" /></edge><edge num="1" var="Disapprove"><decision choice="Obama" end="0" p="1" /></edge></node></edge><edge num="3" var="West"><decision choice="Obama" end="0" p="1" /></edge><edge num="2" var="Midwest"><decision choice="Obama" end="0" p="1" /></edge></node></edge></node><node var="Age"><edge num="1" var="30-44"><decision choice="Obama" end="0" p="1" /></edge><edge num="3" var="65+"><node var="Region"><edge num="1" var="South"><decision choice="Obama" end="0" p="1" /></edge><edge num="2" var="Midwest"><decision choice="Obama" end="0" p="1" /></edge><edge num="0" var="Northeast"><decision choice="Obama" end="0" p="1" /></edge><edge num="3" var="West"><decision choice="McCain" end="1" p="1" /></edge></node></edge><edge num="0" var="18-29"><decision choice="Obama" end="0" p="1" /></edge><edge num="2" var="45-64"><node var="Region"><edge num="2" var="Midwest"><node var="Bush Approval"><edge num="1" var="Disapprove"><decision choice="Obama" end="0" p="1" /></edge><edge num="0" var="Approve"><decision choice="McCain" end="1" p="1" /></edge></node></edge><edge num="0" var="Northeast"><decision choice="Obama" end="0" p="1" /></edge><edge num="1" var="South"><node var="Bush Approval"><edge num="1" var="Disapprove"><decision choice="Obama" end="0" p="1" /></edge><edge num="0" var="Approve"><decision choice="Obama" end="0" p="1" /></edge></node></edge><edge num="3" var="West"><node var="Bush Approval"><edge num="1" var="Disapprove"><decision choice="Obama" end="0" p="1" /></edge><edge num="0" var="Approve"><decision choice="Obama" end="0" p="1" /></edge></node></edge></node></edge></node><node var="Age"><edge num="1" var="30-44"><decision choice="Obama" end="0" p="1" /></edge><edge num="2" var="45-64"><node var="Bush Approval"><edge num="0" var="Approve"><node var="Region"><edge num="1" var="South"><decision choice="McCain" end="1" p="1" /></edge><edge num="2" var="Midwest"><decision choice="Obama" end="0" p="1" /></edge><edge num="3" var="West"><decision choice="Obama" end="0" p="1" /></edge></node></edge><edge num="1" var="Disapprove"><decision choice="Obama" end="0" p="1" /></edge></node></edge><edge num="3" var="65+"><node var="Region"><edge num="0" var="Northeast"><node var="Bush Approval"><edge num="1" var="Disapprove"><decision choice="McCain" end="1" p="1" /></edge><edge num="0" var="Approve"><decision choice="McCain" end="1" p="1" /></edge></node></edge><edge num="1" var="South"><decision choice="McCain" end="1" p="1" /></edge><edge num="2" var="Midwest"><decision choice="Obama" end="0" p="1" /></edge><edge num="3" var="West"><decision choice="McCain" end="1" p="1" /></edge></node></edge><edge num="0" var="18-29"><decision choice="Obama" end="0" p="1" /></edge></node><node var="Age"><edge num="2" var="45-64"><node var="Region"><edge num="1" var="South"><decision choice="Obama" end="0" p="1" /></edge><edge num="2" var="Midwest"><decision choice="Obama" end="0" p="1" /></edge><edge num="3" var="West"><node var="Bush Approval"><edge num="1" var="Disapprove"><decision choice="Obama" end="0" p="1" /></edge><edge num="0" var="Approve"><decision choice="Obama" end="0" p="1" /></edge></node></edge><edge num="0" var="Northeast"><decision choice="Obama" end="0" p="1" /></edge></node></edge><edge num="0" var="18-29"><decision choice="Obama" end="0" p="1" /></edge><edge num="1" var="30-44"><decision choice="Obama" end="0" p="1" /></edge><edge num="3" var="65+"><decision choice="Obama" end="0" p="1" /></edge></node><node var="Bush Approval"><edge num="1" var="Disapprove"><decision choice="Obama" end="0" p="1" /></edge><edge num="0" var="Approve"><node var="Region"><edge num="0" var="Northeast"><node var="Age"><edge num="3" var="65+"><decision choice="Obama" end="0" p="1" /></edge><edge num="2" var="45-64"><decision choice="Obama" end="0" p="1" /></edge><edge num="0" var="18-29"><decision choice="Obama" end="0" p="1" /></edge></node></edge><edge num="3" var="West"><decision choice="Obama" end="0" p="1" /></edge><edge num="2" var="Midwest"><node var="Age"><edge num="0" var="18-29"><decision choice="Obama" end="0" p="1" /></edge><edge num="3" var="65+"><decision choice="Obama" end="0" p="1" /></edge><edge num="1" var="30-44"><decision choice="Obama" end="0" p="1" /></edge><edge num="2" var="45-64"><decision choice="McCain" end="1" p="1" /></edge></node></edge><edge num="1" var="South"><decision choice="Obama" end="0" p="1" /></edge></node></edge></node><node var="Age"><edge num="0" var="18-29"><decision choice="Obama" end="0" p="1" /></edge><edge num="3" var="65+"><node var="Region"><edge num="1" var="South"><node var="Bush Approval"><edge num="1" var="Disapprove"><decision choice="Obama" end="0" p="1" /></edge><edge num="0" var="Approve"><decision choice="McCain" end="1" p="1" /></edge></node></edge><edge num="0" var="Northeast"><decision choice="Obama" end="0" p="1" /></edge><edge num="2" var="Midwest"><decision choice="McCain" end="1" p="1" /></edge><edge num="3" var="West"><node var="Bush Approval"><edge num="0" var="Approve"><decision choice="McCain" end="1" p="1" /></edge><edge num="1" var="Disapprove"><decision choice="McCain" end="1" p="1" /></edge></node></edge></node></edge><edge num="1" var="30-44"><decision choice="Obama" end="0" p="1" /></edge><edge num="2" var="45-64"><node var="Region"><edge num="1" var="South"><node var="Bush Approval"><edge num="1" var="Disapprove"><decision choice="Obama" end="0" p="1" /></edge><edge num="0" var="Approve"><decision choice="McCain" end="1" p="1" /></edge></node></edge><edge num="0" var="Northeast"><decision choice="Obama" end="0" p="1" /></edge><edge num="3" var="West"><decision choice="Obama" end="0" p="1" /></edge><edge num="2" var="Midwest"><decision choice="Obama" end="0" p="1" /></edge></node></edge></node></tree>